boring_math/integer_math/__init__.py
boring_math/integer_math/combinatorics.py
boring_math/integer_math/number_theory.py
boring_math/integer_math/py.typed
boring_math_integer_math-1.2.0.dist-info/licenses/LICENSE
boring_math_integer_math-1.2.0.dist-info/WHEEL
boring_math_integer_math-1.2.0.dist-info/METADATA
boring_math_integer_math-1.2.0.dist-info/RECORD
